wolfprot/__init__.py
wolfprot/connection.py
wolfprot/cynap.py
wolfprot/parser.py
wolfprot/wolfdoc.py
pywolfprot-0.4.dist-info/LICENSE
pywolfprot-0.4.dist-info/METADATA
pywolfprot-0.4.dist-info/WHEEL
pywolfprot-0.4.dist-info/top_level.txt
pywolfprot-0.4.dist-info/RECORD
