Metadata-Version: 2.1
Name: pywolfprot
Version: 0.4
Summary: send and receive wolfvision wolfprot commands
Home-page: https://github.com/stefanu21/pywolfprot
Author: Stefan Ursella
Author-email: stefan.ursella@wolfvision.net
License: GPLv2
Project-URL: Bug Reports, https://github.com/stefanu21/pywolfprot
Project-URL: Source, https://github.com/stefanu21/pywolfprot
Keywords: Wolfvision wolfprot cynap
Platform: UNKNOWN
Classifier: Development Status :: 3 - Alpha
Classifier: License :: OSI Approved :: GNU General Public License v2 (GPLv2)
Classifier: Programming Language :: Python :: 3
Classifier: Intended Audience :: Developers
Classifier: Topic :: Software Development :: Build Tools
Requires-Python: >=3.6
Requires-Dist: websocket-client
